genov/__init__.py
genov/genov.py
genov/atlassian/__init__.py
genov/atlassian/jira/__init__.py
genov/atlassian/jira/get_issues/__init__.py
genov/atlassian/jira/get_issues/jr_gt_iss.py
genov/atlassian/jira/get_issues/jr_gt_iss_typer.py
genov/gsculpt/__init__.py
genov/helpers/__init__.py
genov/helpers/dataframe/__init__.py
genov/helpers/dataframe/df_to_stdout_typer.py
genov/helpers/dataframe/df_to_xlsx_typer.py
genov/helpers/dataframe/df_typer.py
genov/helpers/json/__init__.py
genov/helpers/json/json_cker__checker.py
genov/helpers/json/json_flattener.py
genov/helpers/json/json_to_file_typer.py
genov/helpers/json/json_to_stdout_typer.py
genov/legacy/__init__.py
genov/utils/__init__.py
genov/utils/typer/__init__.py
genov/utils/typer/config/__init__.py
genov/utils/typer/config/config.py
genov/utils/typer/config/config_typer.py
genov/utils/typer/context_obj/__init__.py
genov/utils/typer/context_obj/context_obj.py
genov/utils/typer/custom_types/__init__.py
genov/utils/typer/custom_types/custom_types.py
genov/welcome/__init__.py
genov/welcome/welcome.py
genov/welcome/welcome_typer.py
genov-0.0.4.dist-info/METADATA
genov-0.0.4.dist-info/WHEEL
genov-0.0.4.dist-info/entry_points.txt
genov-0.0.4.dist-info/licenses/LICENSE
genov-0.0.4.dist-info/RECORD
