Metadata-Version: 2.4
Name: genov
Version: 0.0.4
Summary: Genovation toolbox
Project-URL: Homepage, https://bitbucket.org/genovationbit/genov/src/main/
Project-URL: Bug Tracker, https://genovation.atlassian.net/jira/software/c/projects/GENO/list
Project-URL: Documentation, http://www.genovation.fr
Project-URL: Source code, https://bitbucket.org/genovationbit/genov/src/main/
Author-email: jean-sebastien guillard <jsebastien.guillard@gmail.com>
License-File: LICENSE
Classifier: License :: Other/Proprietary License
Classifier: Operating System :: OS Independent
Classifier: Programming Language :: Python :: 3
Requires-Python: >=3.13
Requires-Dist: com-enovation
Requires-Dist: jsonata-python
Requires-Dist: jsonschema
Requires-Dist: pydash
Requires-Dist: tomlkit
Requires-Dist: typer
